.travis.yml
MANIFEST.in
README.rst
base.cfg
buildout.cfg
setup.py
travis.cfg
version.txt
docs/CHANGES.rst
docs/INSTALL.rst
docs/LICENSE.GPL
docs/LICENSE.txt
src/collective/__init__.py
src/collective.z3cform.chosen.egg-info/PKG-INFO
src/collective.z3cform.chosen.egg-info/SOURCES.txt
src/collective.z3cform.chosen.egg-info/dependency_links.txt
src/collective.z3cform.chosen.egg-info/entry_points.txt
src/collective.z3cform.chosen.egg-info/namespace_packages.txt
src/collective.z3cform.chosen.egg-info/requires.txt
src/collective.z3cform.chosen.egg-info/top_level.txt
src/collective/z3cform/__init__.py
src/collective/z3cform/chosen/README.txt
src/collective/z3cform/chosen/__init__.py
src/collective/z3cform/chosen/app_config.py
src/collective/z3cform/chosen/configure.zcml
src/collective/z3cform/chosen/display.pt
src/collective/z3cform/chosen/hidden.pt
src/collective/z3cform/chosen/input.pt
src/collective/z3cform/chosen/interfaces.py
src/collective/z3cform/chosen/profiles.zcml
src/collective/z3cform/chosen/rebuild_i18n.sh
src/collective/z3cform/chosen/setuphandlers.py
src/collective/z3cform/chosen/testing.py
src/collective/z3cform/chosen/version.txt
src/collective/z3cform/chosen/widget.py
src/collective/z3cform/chosen/browser/__init__.py
src/collective/z3cform/chosen/browser/configure.zcml
src/collective/z3cform/chosen/browser/demo/__init__.py
src/collective/z3cform/chosen/browser/demo/configure.zcml
src/collective/z3cform/chosen/browser/demo/demo.py
src/collective/z3cform/chosen/browser/resources/README.txt
src/collective/z3cform/chosen/locales/collective.z3cform.chosen-manual.pot
src/collective/z3cform/chosen/locales/collective.z3cform.chosen.pot
src/collective/z3cform/chosen/locales/fr/LC_MESSAGES/collective.z3cform.chosen.po
src/collective/z3cform/chosen/migrations/__init__.py
src/collective/z3cform/chosen/migrations/configure.zcml
src/collective/z3cform/chosen/migrations/v11/__init__.py
src/collective/z3cform/chosen/migrations/v11/configure.zcml
src/collective/z3cform/chosen/migrations/v11/profile/metadata.xml
src/collective/z3cform/chosen/profiles/default/browserlayer.xml
src/collective/z3cform/chosen/profiles/default/collective.z3cform.chosen_various.txt
src/collective/z3cform/chosen/profiles/default/controlpanel.xml
src/collective/z3cform/chosen/profiles/default/cssregistry.xml
src/collective/z3cform/chosen/profiles/default/jsregistry.xml
