Metadata-Version: 2.1
Name: collective.z3cform.chosen
Version: 1.2.2
Summary: chosen widget for z3cform (both chosen & ajax version)
Home-page: http://pypi.python.org/pypi/collective.z3cform.chosen
Author: kiorky
Author-email: kiorky@cryptelium.net
License: GPL
Keywords: chosen z3cform widget plone
Platform: UNKNOWN
Classifier: Framework :: Plone
Classifier: Framework :: Plone :: 4.0
Classifier: Framework :: Plone :: 4.1
Classifier: Framework :: Plone :: 4.2
Classifier: Programming Language :: Python
Classifier: Topic :: Software Development
Provides-Extra: test
